setup.py
django_checksum.egg-info/PKG-INFO
django_checksum.egg-info/SOURCES.txt
django_checksum.egg-info/dependency_links.txt
django_checksum.egg-info/top_level.txt
src/__init__.py
src/admin.py
src/models.py