Metadata-Version: 1.1
Name: django-checksum
Version: 0.1.rec68f42a975e
Summary: Django checksum app
Home-page: http://bitbucket.org/lars512/django-checksum/
Author: Lars Yencken
Author-email: lljy@csse.unimelb.edu.au
License: GPL
Platform: UNKNOWN
Requires: django (>= 1.0)
